literature/__init__.py
literature/utils.py
literature/cards/__init__.py
literature/cards/card.py
literature/cards/deck.py
literature/cards/rank.py
literature/cards/suit.py
literature/game/__init__.py
literature/game/errors.py
literature/game/game.py
literature/game/move.py
literature/parser/__init__.py
literature/parser/errors.py
literature/parser/move_parser.py
literature/viz/grid.py
literature/viz/readme.md
lit_engine-0.0.1.dev0.dist-info/METADATA
lit_engine-0.0.1.dev0.dist-info/WHEEL
lit_engine-0.0.1.dev0.dist-info/RECORD
